CHANGES.txt
CONTRIBUTING.md
COPYRIGHT.txt
LICENSE.md
LICENSE.third-party.txt
MANIFEST.in
README.md
requirements.txt
set-env.sh
setup.py
ck/__init__.py
ck/__main__.py
ck/files.py
ck/kernel.py
ck/net.py
ck/strings.py
ck.egg-info/PKG-INFO
ck.egg-info/SOURCES.txt
ck.egg-info/dependency_links.txt
ck.egg-info/entry_points.txt
ck.egg-info/not-zip-safe
ck.egg-info/requires.txt
ck.egg-info/top_level.txt
ck/repo/.ck.cache_repo_info.json
ck/repo/.ck.cache_repo_uoa.json
ck/repo/.ckr.json
ck/repo/.cm/alias-a-kernel
ck/repo/.cm/alias-a-module
ck/repo/.cm/alias-a-repo
ck/repo/.cm/alias-a-test
ck/repo/.cm/alias-u-032630d041b4fd8a
ck/repo/.cm/alias-u-942e180ee60b2d72
ck/repo/.cm/alias-u-b1e99f6461424276
ck/repo/.cm/alias-u-befd7892b0d469e9
ck/repo/kernel/.cm/alias-a-default
ck/repo/kernel/.cm/alias-u-394b518a52bedf07
ck/repo/kernel/default/.cm/info.json
ck/repo/kernel/default/.cm/meta.json
ck/repo/module/.cm/alias-a-advice
ck/repo/module/.cm/alias-a-algorithm
ck/repo/module/.cm/alias-a-all
ck/repo/module/.cm/alias-a-apk
ck/repo/module/.cm/alias-a-artifact
ck/repo/module/.cm/alias-a-caffe2
ck/repo/module/.cm/alias-a-cfg
ck/repo/module/.cm/alias-a-choice
ck/repo/module/.cm/alias-a-ck-platform
ck/repo/module/.cm/alias-a-clblast
ck/repo/module/.cm/alias-a-cmdgen
ck/repo/module/.cm/alias-a-compiler
ck/repo/module/.cm/alias-a-crowdnode
ck/repo/module/.cm/alias-a-dashboard
ck/repo/module/.cm/alias-a-dataset
ck/repo/module/.cm/alias-a-dataset.features
ck/repo/module/.cm/alias-a-demo
ck/repo/module/.cm/alias-a-device
ck/repo/module/.cm/alias-a-doc
ck/repo/module/.cm/alias-a-docker
ck/repo/module/.cm/alias-a-docker.template
ck/repo/module/.cm/alias-a-docs
ck/repo/module/.cm/alias-a-env
ck/repo/module/.cm/alias-a-experiment
ck/repo/module/.cm/alias-a-experiment.bench.caffe2
ck/repo/module/.cm/alias-a-experiment.bench.dnn
ck/repo/module/.cm/alias-a-experiment.bench.dnn.mobile
ck/repo/module/.cm/alias-a-experiment.bench.tensorflow
ck/repo/module/.cm/alias-a-experiment.check.algorithm.scalability
ck/repo/module/.cm/alias-a-experiment.check.numerical.stability
ck/repo/module/.cm/alias-a-experiment.detect.opencl.bugs
ck/repo/module/.cm/alias-a-experiment.model.program.behavior
