Metadata-Version: 2.1
Name: ck
Version: 2.6.4
Summary: Collective Knowledge - a lightweight knowledge manager to organize, cross-link, share and reuse artifacts and workflows based on FAIR principles
Home-page: https://github.com/mlcommons/ck
Author: Grigori Fursin
Author-email: Grigori.Fursin@cTuning.org
License: Apache 2.0
Classifier: Programming Language :: Python
Classifier: Programming Language :: Python :: 3
Classifier: Development Status :: 5 - Production/Stable
Classifier: Environment :: Console
Classifier: Environment :: Plugins
Classifier: Environment :: Web Environment
Classifier: Intended Audience :: Developers
Classifier: Intended Audience :: Education
Classifier: Intended Audience :: End Users/Desktop
Classifier: Intended Audience :: Information Technology
Classifier: Intended Audience :: Science/Research
Classifier: Operating System :: OS Independent
Classifier: Topic :: Scientific/Engineering :: Information Analysis
Classifier: Topic :: Scientific/Engineering
Classifier: Topic :: Software Development
Classifier: Topic :: System
Classifier: Topic :: System :: Benchmark
Classifier: Topic :: Education
Classifier: Topic :: Home Automation
Classifier: Topic :: Adaptive Technologies
Classifier: Topic :: Database
Classifier: Topic :: Utilities
License-File: LICENSE.md
License-File: LICENSE.third-party.txt
